Metadata-Version: 1.0
Name: setuptools-darcs
Version: 1.2.10
Summary: setuptools plugin for darcs
Home-page: http://allmydata.org/trac/setuptools_darcs
Author: Zooko O'Whielacronx
Author-email: zooko@zooko.com
License: BSD
Keywords: distutils setuptools setup darcs
Platform: UNKNOWN
Classifier: Framework :: Setuptools Plugin
Classifier: Development Status :: 5 - Production/Stable
Classifier: License :: OSI Approved :: BSD License
Classifier: License :: DFSG approved
Classifier: Intended Audience :: Developers
Classifier: Operating System :: Microsoft
Classifier: Operating System :: Microsoft :: Windows
Classifier: Operating System :: Unix
Classifier: Operating System :: POSIX :: Linux
Classifier: Operating System :: POSIX
Classifier: Operating System :: MacOS :: MacOS X
Classifier: Operating System :: Microsoft :: Windows :: Windows NT/2000
Classifier: Operating System :: OS Independent
Classifier: Natural Language :: English
Classifier: Programming Language :: Python
Classifier: Programming Language :: Python :: 2
Classifier: Programming Language :: Python :: 2.4
Classifier: Programming Language :: Python :: 2.5
Classifier: Programming Language :: Python :: 2.6
Classifier: Topic :: Utilities
Classifier: Topic :: Software Development :: Libraries
